sorcery/__init__.py
sorcery/core.py
sorcery/spells.py
sorcery/version.py
sorcery-0.2.2.dist-info/LICENSE.txt
sorcery-0.2.2.dist-info/METADATA
sorcery-0.2.2.dist-info/WHEEL
sorcery-0.2.2.dist-info/top_level.txt
sorcery-0.2.2.dist-info/RECORD
